gpt4all_code_review/__init__.py
gpt4all_code_review/gpt4all_code_review.py
gpt4all_tone/__init__.py
gpt4all_tone/gpt4all_tone.py
gpt4all_tone-0.23.dist-info/METADATA
gpt4all_tone-0.23.dist-info/WHEEL
gpt4all_tone-0.23.dist-info/entry_points.txt
gpt4all_tone-0.23.dist-info/top_level.txt
gpt4all_tone-0.23.dist-info/RECORD
