Metadata-Version: 2.1
Name: gpt4all-tone
Version: 0.23
Summary: A comprehensive tool for sentiment analysis and tone review, empowered by GPT4ALL.
Home-page: https://github.com/chigwell/gpt4all-tone
Author: Evgenii Evstafev
Author-email: chigwel@gmail.com
Requires-Dist: argparse
Requires-Dist: gpt4all
